DjangoAppCenter/__init__.py
DjangoAppCenter/__main__.py
DjangoAppCenter/cli.py
DjangoAppCenter/manage.py
DjangoAppCenter/utils.py
DjangoAppCenter/wsgi.py
DjangoAppCenter/extensions/__init__.py
DjangoAppCenter/extensions/apps/__init__.py
DjangoAppCenter/extensions/apps/permission_init.py
DjangoAppCenter/extensions/fields/__init__.py
DjangoAppCenter/extensions/fields/snowflake/__init__.py
DjangoAppCenter/extensions/fields/snowflake/config.py
DjangoAppCenter/extensions/fields/snowflake/core.py
DjangoAppCenter/extensions/fields/snowflake/field.py
DjangoAppCenter/packages/__init__.py
DjangoAppCenter/packages/admin.py
DjangoAppCenter/packages/apps.py
DjangoAppCenter/packages/models.py
DjangoAppCenter/packages/tests.py
DjangoAppCenter/packages/views.py
DjangoAppCenter/packages/migrations/0001_initial.py
DjangoAppCenter/packages/migrations/0002_package_settings.py
DjangoAppCenter/packages/migrations/__init__.py
DjangoAppCenter/settings/__init__.py
DjangoAppCenter/settings/asgi.py
DjangoAppCenter/settings/dbrouters.py
DjangoAppCenter/settings/loader.py
DjangoAppCenter/settings/log.py
DjangoAppCenter/settings/urls.py
DjangoAppCenter/settings/migrations/0001_initial.py
DjangoAppCenter/settings/migrations/0002_auto_20210325_1121.py
DjangoAppCenter/settings/migrations/__init__.py
DjangoAppCenter/settings/templates/Dockerfile
DjangoAppCenter/settings/templates/db.default.sqlite3
DjangoAppCenter/settings/templates/settings.default.json
DjangoAppCenter/signals/__init__.py
DjangoAppCenter/signals/restart.py
DjangoAppCenter-0.9.16.dist-info/AUTHORS
DjangoAppCenter-0.9.16.dist-info/METADATA
DjangoAppCenter-0.9.16.dist-info/WHEEL
DjangoAppCenter-0.9.16.dist-info/entry_points.txt
DjangoAppCenter-0.9.16.dist-info/pbr.json
DjangoAppCenter-0.9.16.dist-info/top_level.txt
DjangoAppCenter-0.9.16.dist-info/RECORD
