Metadata-Version: 2.1
Name: DjangoAppCenter
Version: 0.9.16
Summary: Django Apps Container.
Home-page: http://example.com
Author: singein
Author-email: singein@outlook.com
License: MIT
Platform: UNKNOWN
Requires-Dist: django-cors-headers (==3.3.0)
Requires-Dist: django (==3.0.2)
Requires-Dist: django-filter (==2.2.0)
Requires-Dist: fire
